mcai_worker_sdk_media-2.1.1.dist-info/METADATA
mcai_worker_sdk_media-2.1.1.dist-info/WHEEL
mcai_worker_sdk_media-2.1.1.dist-info/licenses/LICENSE
mcai_worker_sdk.libs/libflite_cmulex-dfbdbb46.so.1
mcai_worker_sdk.libs/libva-drm-9cf5b3c1.so.2
mcai_worker_sdk.libs/libk5crypto-6f3ba266.so.3
mcai_worker_sdk.libs/libcom_err-f196091d.so.2
mcai_worker_sdk.libs/libflite_cmu_us_kal16-69a5f02a.so.1
mcai_worker_sdk.libs/libserd-0-0370a8cb.so.0
mcai_worker_sdk.libs/libzimg-41e16479.so.2
mcai_worker_sdk.libs/libbrotlicommon-abf86ae9.so.1
mcai_worker_sdk.libs/libtheoradec-ed8da085.so.1
mcai_worker_sdk.libs/libgio-2-1b52fff8.0.so.0
mcai_worker_sdk.libs/libflite-fb35e671.so.1
mcai_worker_sdk.libs/libpcre2-8-f887eed7.so.0
mcai_worker_sdk.libs/libkrb5-d42e9f9a.so.3
mcai_worker_sdk.libs/libgssapi_krb5-0e3e5402.so.2
mcai_worker_sdk.libs/liblzma-493cb401.so.5
mcai_worker_sdk.libs/liblapack-86b2c207.so.3
mcai_worker_sdk.libs/libwebpmux-28f31053.so.3
mcai_worker_sdk.libs/libbluray-c8166773.so.2
mcai_worker_sdk.libs/libunistring-9c28d595.so.2
mcai_worker_sdk.libs/libpostproc-a721eace.so.55
mcai_worker_sdk.libs/libgme-a49d1977.so.0
mcai_worker_sdk.libs/libsrt-gnutls-9eab20d9.so.1.4
mcai_worker_sdk.libs/libtasn1-02557ad1.so.6
mcai_worker_sdk.libs/libxvidcore-5421e7c0.so.4
mcai_worker_sdk.libs/libnuma-3582bce9.so.1
mcai_worker_sdk.libs/libkeyutils-ad20d5fb.so.1
mcai_worker_sdk.libs/libdatrie-bb12f6de.so.1
mcai_worker_sdk.libs/libdav1d-eb4b11f1.so.5
mcai_worker_sdk.libs/libgmp-4dc20a90.so.10
mcai_worker_sdk.libs/libpgm-5-fcc27728.3.so.0
mcai_worker_sdk.libs/libass-14850341.so.9
mcai_worker_sdk.libs/libXau-98343a83.so.6
mcai_worker_sdk.libs/libzvbi-8cec6535.so.0
mcai_worker_sdk.libs/libquadmath-1c3f8ec4.so.0
mcai_worker_sdk.libs/libOpenCL-3fc4989d.so.1
mcai_worker_sdk.libs/libtwolame-192bf57f.so.0
mcai_worker_sdk.libs/libopenjp2-b16af866.so.7
mcai_worker_sdk.libs/librubberband-ad027488.so.2
mcai_worker_sdk.libs/libnorm-cc5c631e.so.1
mcai_worker_sdk.libs/libuuid-1c523104.so.1
mcai_worker_sdk.libs/libopenmpt-9f9fc45a.so.0
mcai_worker_sdk.libs/libicudata-c1404396.so.70
mcai_worker_sdk.libs/libflite_cmu_us_awb-34bd371d.so.1
mcai_worker_sdk_media-2.1.1.dist-info/RECORD
